{
  "id": "tradle.Country",
  "subClassOf": "tradle.Enum",
  "title": "title",
  "sort": "title",
  "type": "tradle.Model",
  "properties": {
    "title": {
      "displayName": true,
      "type": "string"
    }
  },
  "enum": [
    {
      "numeric": 20,
      "id": "AD",
      "cca3": "AND",
      "title": "Andorra",
      "nationality": "Andorran"
    },
    {
      "numeric": 784,
      "id": "AE",
      "cca3": "ARE",
      "title": "United Arab Emirates",
      "nationality": "Emirati, Emirian, Emiri"
    },
    {
      "numeric": 4,
      "id": "AF",
      "cca3": "AFG",
      "title": "Afghanistan",
      "nationality": "Afghan"
    },
    {
      "numeric": 28,
      "id": "AG",
      "cca3": "ATG",
      "title": "Antigua and Barbuda",
      "nationality": "Antiguan or Barbudan"
    },
    {
      "numeric": 660,
      "id": "AI",
      "cca3": "AIA",
      "title": "Anguilla",
      "nationality": "Anguillan"
    },
    {
      "numeric": 8,
      "id": "AL",
      "cca3": "ALB",
      "title": "Albania",
      "nationality": "Albanian"
    },
    {
      "numeric": 51,
      "id": "AM",
      "cca3": "ARM",
      "title": "Armenia",
      "nationality": "Armenian"
    },
    {
      "numeric": 24,
      "id": "AO",
      "cca3": "AGO",
      "title": "Angola",
      "nationality": "Angolan"
    },
    {
      "numeric": 10,
      "id": "AQ",
      "cca3": "ATA",
      "title": "Antarctica",
      "nationality": "Antarctic"
    },
    {
      "numeric": 32,
      "id": "AR",
      "cca3": "ARG",
      "title": "Argentina",
      "nationality": "Argentine"
    },
    {
      "numeric": 16,
      "id": "AS",
      "cca3": "ASM",
      "title": "American Samoa",
      "nationality": "American Samoan"
    },
    {
      "numeric": 40,
      "id": "AT",
      "cca3": "AUT",
      "title": "Austria",
      "nationality": "Austrian"
    },
    {
      "numeric": 36,
      "id": "AU",
      "cca3": "AUS",
      "title": "Australia",
      "nationality": "Australian"
    },
    {
      "numeric": 533,
      "id": "AW",
      "cca3": "ABW",
      "title": "Aruba",
      "nationality": "Aruban"
    },
    {
      "numeric": 248,
      "id": "AX",
      "cca3": "ALA",
      "title": "Öland Islands",
      "nationality": "Åland Island"
    },
    {
      "numeric": 31,
      "id": "AZ",
      "cca3": "AZE",
      "title": "Azerbaijan",
      "nationality": "Azerbaijani, Azeri"
    },
    {
      "numeric": 70,
      "id": "BA",
      "cca3": "BIH",
      "title": "Bosnia and Herzegovina",
      "nationality": "Bosnian or Herzegovinian"
    },
    {
      "numeric": 52,
      "id": "BB",
      "cca3": "BRB",
      "title": "Barbados",
      "nationality": "Barbadian"
    },
    {
      "numeric": 50,
      "id": "BD",
      "cca3": "BGD",
      "title": "Bangladesh",
      "nationality": "Bangladeshi"
    },
    {
      "numeric": 56,
      "id": "BE",
      "cca3": "BEL",
      "title": "Belgium",
      "nationality": "Belgian"
    },
    {
      "numeric": 854,
      "id": "BF",
      "cca3": "BFA",
      "title": "Burkina Faso",
      "nationality": "Burkinabé"
    },
    {
      "numeric": 100,
      "id": "BG",
      "cca3": "BGR",
      "title": "Bulgaria",
      "nationality": "Bulgarian"
    },
    {
      "numeric": 48,
      "id": "BH",
      "cca3": "BHR",
      "title": "Bahrain",
      "nationality": "Bahraini"
    },
    {
      "numeric": 108,
      "id": "BI",
      "cca3": "BDI",
      "title": "Burundi",
      "nationality": "Burundian"
    },
    {
      "numeric": 204,
      "id": "BJ",
      "cca3": "BEN",
      "title": "Benin",
      "nationality": "Beninese, Beninois"
    },
    {
      "numeric": 652,
      "id": "BL",
      "cca3": "BLM",
      "title": "Saint Barthélemy",
      "nationality": "Barthélemois"
    },
    {
      "numeric": 60,
      "id": "BM",
      "cca3": "BMU",
      "title": "Bermuda",
      "nationality": "Bermudian, Bermudan"
    },
    {
      "numeric": 96,
      "id": "BN",
      "cca3": "BRN",
      "title": "Brunei Darussalam",
      "nationality": "Bruneian"
    },
    {
      "numeric": 68,
      "id": "BO",
      "cca3": "BOL",
      "title": "Bolivia",
      "nationality": "Bolivian"
    },
    {
      "numeric": 535,
      "id": "BQ",
      "cca3": "BES",
      "title": "Caribbean Netherlands ",
      "nationality": "Bonaire"
    },
    {
      "numeric": 76,
      "id": "BR",
      "cca3": "BRA",
      "title": "Brazil",
      "nationality": "Brazilian"
    },
    {
      "numeric": 44,
      "id": "BS",
      "cca3": "BHS",
      "title": "Bahamas",
      "nationality": "Bahamian"
    },
    {
      "numeric": 64,
      "id": "BT",
      "cca3": "BTN",
      "title": "Bhutan",
      "nationality": "Bhutanese"
    },
    {
      "numeric": 74,
      "id": "BV",
      "cca3": "BVT",
      "title": "Bouvet Island",
      "nationality": "Bouvet Island"
    },
    {
      "numeric": 72,
      "id": "BW",
      "cca3": "BWA",
      "title": "Botswana",
      "nationality": "Motswana, Botswanan"
    },
    {
      "numeric": 112,
      "id": "BY",
      "cca3": "BLR",
      "title": "Belarus",
      "nationality": "Belarusian"
    },
    {
      "numeric": 84,
      "id": "BZ",
      "cca3": "BLZ",
      "title": "Belize",
      "nationality": "Belizean"
    },
    {
      "numeric": 124,
      "id": "CA",
      "cca3": "CAN",
      "title": "Canada",
      "nationality": "Canadian"
    },
    {
      "numeric": 166,
      "id": "CC",
      "cca3": "CCK",
      "title": "Cocos (Keeling) Islands",
      "nationality": "Cocos Island"
    },
    {
      "numeric": 180,
      "id": "CD",
      "cca3": "COD",
      "title": "Congo, Democratic Republic of",
      "nationality": "Congolese"
    },
    {
      "numeric": 140,
      "id": "CF",
      "cca3": "CAF",
      "title": "Central African Republic",
      "nationality": "Central African"
    },
    {
      "numeric": 178,
      "id": "CG",
      "cca3": "COG",
      "title": "Congo",
      "nationality": "Congolese"
    },
    {
      "numeric": 756,
      "id": "CH",
      "cca3": "CHE",
      "title": "Switzerland",
      "nationality": "Swiss"
    },
    {
      "numeric": 384,
      "id": "CI",
      "cca3": "CIV",
      "title": "Côte d'Ivoire",
      "nationality": "Ivorian"
    },
    {
      "numeric": 184,
      "id": "CK",
      "cca3": "COK",
      "title": "Cook Islands",
      "nationality": "Cook Island"
    },
    {
      "numeric": 152,
      "id": "CL",
      "cca3": "CHL",
      "title": "Chile",
      "nationality": "Chilean"
    },
    {
      "numeric": 120,
      "id": "CM",
      "cca3": "CMR",
      "title": "Cameroon",
      "nationality": "Cameroonian"
    },
    {
      "numeric": 156,
      "id": "CN",
      "cca3": "CHN",
      "title": "China",
      "nationality": "Chinese"
    },
    {
      "numeric": 170,
      "id": "CO",
      "cca3": "COL",
      "title": "Colombia",
      "nationality": "Colombian"
    },
    {
      "numeric": 188,
      "id": "CR",
      "cca3": "CRI",
      "title": "Costa Rica",
      "nationality": "Costa Rican"
    },
    {
      "numeric": 192,
      "id": "CU",
      "cca3": "CUB",
      "title": "Cuba",
      "nationality": "Cuban"
    },
    {
      "numeric": 132,
      "id": "CV",
      "cca3": "CPV",
      "title": "Cape Verde",
      "nationality": "Cabo Verdean"
    },
    {
      "numeric": 531,
      "id": "CW",
      "cca3": "CUW",
      "title": "Curaçao",
      "nationality": "Curaçaoan"
    },
    {
      "numeric": 162,
      "id": "CX",
      "cca3": "CXR",
      "title": "Christmas Island",
      "nationality": "Christmas Island"
    },
    {
      "numeric": 196,
      "id": "CY",
      "cca3": "CYP",
      "title": "Cyprus",
      "nationality": "Cypriot"
    },
    {
      "numeric": 203,
      "id": "CZ",
      "cca3": "CZE",
      "title": "Czech Republic",
      "nationality": "Czech"
    },
    {
      "numeric": 276,
      "id": "DE",
      "cca3": "DEU",
      "title": "Germany",
      "nationality": "German"
    },
    {
      "numeric": 262,
      "id": "DJ",
      "cca3": "DJI",
      "title": "Djibouti",
      "nationality": "Djiboutian"
    },
    {
      "numeric": 208,
      "id": "DK",
      "cca3": "DNK",
      "title": "Denmark",
      "nationality": "Danish"
    },
    {
      "numeric": 212,
      "id": "DM",
      "cca3": "DMA",
      "title": "Dominica",
      "nationality": "Dominican"
    },
    {
      "numeric": 214,
      "id": "DO",
      "cca3": "DOM",
      "title": "Dominican Republic",
      "nationality": "Dominican"
    },
    {
      "numeric": 12,
      "id": "DZ",
      "cca3": "DZA",
      "title": "Algeria",
      "nationality": "Algerian"
    },
    {
      "numeric": 218,
      "id": "EC",
      "cca3": "ECU",
      "title": "Ecuador",
      "nationality": "Ecuadorian"
    },
    {
      "numeric": 233,
      "id": "EE",
      "cca3": "EST",
      "title": "Estonia",
      "nationality": "Estonian"
    },
    {
      "numeric": 818,
      "id": "EG",
      "cca3": "EGY",
      "title": "Egypt",
      "nationality": "Egyptian"
    },
    {
      "numeric": 732,
      "id": "EH",
      "cca3": "ESH",
      "title": "Western Sahara",
      "nationality": "Sahrawi, Sahrawian, Sahraouian"
    },
    {
      "numeric": 232,
      "id": "ER",
      "cca3": "ERI",
      "title": "Eritrea",
      "nationality": "Eritrean"
    },
    {
      "numeric": 724,
      "id": "ES",
      "cca3": "ESP",
      "title": "Spain",
      "nationality": "Spanish"
    },
    {
      "numeric": 231,
      "id": "ET",
      "cca3": "ETH",
      "title": "Ethiopia",
      "nationality": "Ethiopian"
    },
    {
      "numeric": 246,
      "id": "FI",
      "cca3": "FIN",
      "title": "Finland",
      "nationality": "Finnish"
    },
    {
      "numeric": 242,
      "id": "FJ",
      "cca3": "FJI",
      "title": "Fiji",
      "nationality": "Fijian"
    },
    {
      "numeric": 238,
      "id": "FK",
      "cca3": "FLK",
      "title": "Falkland Islands",
      "nationality": "Falkland Island"
    },
    {
      "numeric": 583,
      "id": "FM",
      "cca3": "FSM",
      "title": "Micronesia, Federated States of",
      "nationality": "Micronesian"
    },
    {
      "numeric": 234,
      "id": "FO",
      "cca3": "FRO",
      "title": "Faroe Islands",
      "nationality": "Faroese"
    },
    {
      "numeric": 250,
      "id": "FR",
      "cca3": "FRA",
      "title": "France",
      "nationality": "French"
    },
    {
      "numeric": 266,
      "id": "GA",
      "cca3": "GAB",
      "title": "Gabon",
      "nationality": "Gabonese"
    },
    {
      "numeric": 826,
      "id": "GB",
      "cca3": "GBR",
      "title": "United Kingdom",
      "nationality": "British, UK"
    },
    {
      "numeric": 308,
      "id": "GD",
      "cca3": "GRD",
      "title": "Grenada",
      "nationality": "Grenadian"
    },
    {
      "numeric": 268,
      "id": "GE",
      "cca3": "GEO",
      "title": "Georgia",
      "nationality": "Georgian"
    },
    {
      "numeric": 254,
      "id": "GF",
      "cca3": "GUF",
      "title": "French Guiana",
      "nationality": "French Guianese"
    },
    {
      "numeric": 831,
      "id": "GG",
      "cca3": "GGY",
      "title": "Guernsey",
      "nationality": "Channel Island"
    },
    {
      "numeric": 288,
      "id": "GH",
      "cca3": "GHA",
      "title": "Ghana",
      "nationality": "Ghanaian"
    },
    {
      "numeric": 292,
      "id": "GI",
      "cca3": "GIB",
      "title": "Gibraltar",
      "nationality": "Gibraltar"
    },
    {
      "numeric": 304,
      "id": "GL",
      "cca3": "GRL",
      "title": "Greenland",
      "nationality": "Greenlandic"
    },
    {
      "numeric": 270,
      "id": "GM",
      "cca3": "GMB",
      "title": "Gambia",
      "nationality": "Gambian"
    },
    {
      "numeric": 324,
      "id": "GN",
      "cca3": "GIN",
      "title": "Guinea",
      "nationality": "Guinean"
    },
    {
      "numeric": 312,
      "id": "GP",
      "cca3": "GLP",
      "title": "Guadeloupe",
      "nationality": "Guadeloupe"
    },
    {
      "numeric": 226,
      "id": "GQ",
      "cca3": "GNQ",
      "title": "Equatorial Guinea",
      "nationality": "Equatorial Guinean, Equatoguinean"
    },
    {
      "numeric": 300,
      "id": "GR",
      "cca3": "GRC",
      "title": "Greece",
      "nationality": "Greek, Hellenic"
    },
    {
      "numeric": 239,
      "id": "GS",
      "cca3": "SGS",
      "title": "South Georgia and the South Sandwich Islands",
      "nationality": "South Georgia or South Sandwich Islands"
    },
    {
      "numeric": 320,
      "id": "GT",
      "cca3": "GTM",
      "title": "Guatemala",
      "nationality": "Guatemalan"
    },
    {
      "numeric": 316,
      "id": "GU",
      "cca3": "GUM",
      "title": "Guam",
      "nationality": "Guamanian, Guambat"
    },
    {
      "numeric": 624,
      "id": "GW",
      "cca3": "GNB",
      "title": "Guinea-Bissau",
      "nationality": "Bissau-Guinean"
    },
    {
      "numeric": 328,
      "id": "GY",
      "cca3": "GUY",
      "title": "Guyana",
      "nationality": "Guyanese"
    },
    {
      "numeric": 344,
      "id": "HK",
      "cca3": "HKG",
      "title": "Hong Kong",
      "nationality": "Hong Kong, Hong Kongese"
    },
    {
      "numeric": 334,
      "id": "HM",
      "cca3": "HMD",
      "title": "Heard and McDonald Islands",
      "nationality": "Heard Island or McDonald Islands"
    },
    {
      "numeric": 340,
      "id": "HN",
      "cca3": "HND",
      "title": "Honduras",
      "nationality": "Honduran"
    },
    {
      "numeric": 191,
      "id": "HR",
      "cca3": "HRV",
      "title": "Croatia",
      "nationality": "Croatian"
    },
    {
      "numeric": 332,
      "id": "HT",
      "cca3": "HTI",
      "title": "Haiti",
      "nationality": "Haitian"
    },
    {
      "numeric": 348,
      "id": "HU",
      "cca3": "HUN",
      "title": "Hungary",
      "nationality": "Hungarian, Magyar"
    },
    {
      "numeric": 360,
      "id": "ID",
      "cca3": "IDN",
      "title": "Indonesia",
      "nationality": "Indonesian"
    },
    {
      "numeric": 372,
      "id": "IE",
      "cca3": "IRL",
      "title": "Ireland",
      "nationality": "Irish"
    },
    {
      "numeric": 376,
      "id": "IL",
      "cca3": "ISR",
      "title": "Israel",
      "nationality": "Israeli"
    },
    {
      "numeric": 833,
      "id": "IM",
      "cca3": "IMN",
      "title": "Isle of Man",
      "nationality": "Manx"
    },
    {
      "numeric": 356,
      "id": "IN",
      "cca3": "IND",
      "title": "India",
      "nationality": "Indian"
    },
    {
      "numeric": 86,
      "id": "IO",
      "cca3": "IOT",
      "title": "British Indian Ocean Territory",
      "nationality": "BIOT"
    },
    {
      "numeric": 368,
      "id": "IQ",
      "cca3": "IRQ",
      "title": "Iraq",
      "nationality": "Iraqi"
    },
    {
      "numeric": 364,
      "id": "IR",
      "cca3": "IRN",
      "title": "Iran",
      "nationality": "Iranian, Persian"
    },
    {
      "numeric": 352,
      "id": "IS",
      "cca3": "ISL",
      "title": "Iceland",
      "nationality": "Icelandic"
    },
    {
      "numeric": 380,
      "id": "IT",
      "cca3": "ITA",
      "title": "Italy",
      "nationality": "Italian"
    },
    {
      "numeric": 832,
      "id": "JE",
      "cca3": "JEY",
      "title": "Jersey",
      "nationality": "Channel Island"
    },
    {
      "numeric": 388,
      "id": "JM",
      "cca3": "JAM",
      "title": "Jamaica",
      "nationality": "Jamaican"
    },
    {
      "numeric": 400,
      "id": "JO",
      "cca3": "JOR",
      "title": "Jordan",
      "nationality": "Jordanian"
    },
    {
      "numeric": 392,
      "id": "JP",
      "cca3": "JPN",
      "title": "Japan",
      "nationality": "Japanese"
    },
    {
      "numeric": 404,
      "id": "KE",
      "cca3": "KEN",
      "title": "Kenya",
      "nationality": "Kenyan"
    },
    {
      "numeric": 417,
      "id": "KG",
      "cca3": "KGZ",
      "title": "Kyrgyzstan",
      "nationality": "Kyrgyzstani, Kyrgyz, Kirgiz, Kirghiz"
    },
    {
      "numeric": 116,
      "id": "KH",
      "cca3": "KHM",
      "title": "Cambodia",
      "nationality": "Cambodian"
    },
    {
      "numeric": 296,
      "id": "KI",
      "cca3": "KIR",
      "title": "Kiribati",
      "nationality": "I-Kiribati"
    },
    {
      "numeric": 174,
      "id": "KM",
      "cca3": "COM",
      "title": "Comoros",
      "nationality": "Comoran, Comorian"
    },
    {
      "numeric": 659,
      "id": "KN",
      "cca3": "KNA",
      "title": "Saint Kitts and Nevis",
      "nationality": "Kittitian or Nevisian"
    },
    {
      "numeric": 408,
      "id": "KP",
      "cca3": "PRK",
      "title": "North Korea",
      "nationality": "North Korean"
    },
    {
      "numeric": 410,
      "id": "KR",
      "cca3": "KOR",
      "title": "South Korea",
      "nationality": "South Korean"
    },
    {
      "numeric": 414,
      "id": "KW",
      "cca3": "KWT",
      "title": "Kuwait",
      "nationality": "Kuwaiti"
    },
    {
      "numeric": 136,
      "id": "KY",
      "cca3": "CYM",
      "title": "Cayman Islands",
      "nationality": "Caymanian"
    },
    {
      "numeric": 398,
      "id": "KZ",
      "cca3": "KAZ",
      "title": "Kazakhstan",
      "nationality": "Kazakhstani, Kazakh"
    },
    {
      "numeric": 418,
      "id": "LA",
      "cca3": "LAO",
      "title": "Lao People's Democratic Republic",
      "nationality": "Lao, Laotian"
    },
    {
      "numeric": 422,
      "id": "LB",
      "cca3": "LBN",
      "title": "Lebanon",
      "nationality": "Lebanese"
    },
    {
      "numeric": 662,
      "id": "LC",
      "cca3": "LCA",
      "title": "Saint Lucia",
      "nationality": "Saint Lucian"
    },
    {
      "numeric": 438,
      "id": "LI",
      "cca3": "LIE",
      "title": "Liechtenstein",
      "nationality": "Liechtenstein"
    },
    {
      "numeric": 144,
      "id": "LK",
      "cca3": "LKA",
      "title": "Sri Lanka",
      "nationality": "Sri Lankan"
    },
    {
      "numeric": 430,
      "id": "LR",
      "cca3": "LBR",
      "title": "Liberia",
      "nationality": "Liberian"
    },
    {
      "numeric": 426,
      "id": "LS",
      "cca3": "LSO",
      "title": "Lesotho",
      "nationality": "Basotho"
    },
    {
      "numeric": 440,
      "id": "LT",
      "cca3": "LTU",
      "title": "Lithuania",
      "nationality": "Lithuanian"
    },
    {
      "numeric": 442,
      "id": "LU",
      "cca3": "LUX",
      "title": "Luxembourg",
      "nationality": "Luxembourg, Luxembourgish"
    },
    {
      "numeric": 428,
      "id": "LV",
      "cca3": "LVA",
      "title": "Latvia",
      "nationality": "Latvian"
    },
    {
      "numeric": 434,
      "id": "LY",
      "cca3": "LBY",
      "title": "Libya",
      "nationality": "Libyan"
    },
    {
      "numeric": 504,
      "id": "MA",
      "cca3": "MAR",
      "title": "Morocco",
      "nationality": "Moroccan"
    },
    {
      "numeric": 492,
      "id": "MC",
      "cca3": "MCO",
      "title": "Monaco",
      "nationality": "Monégasque, Monacan"
    },
    {
      "numeric": 498,
      "id": "MD",
      "cca3": "MDA",
      "title": "Moldova",
      "nationality": "Moldovan"
    },
    {
      "numeric": 499,
      "id": "ME",
      "cca3": "MNE",
      "title": "Montenegro",
      "nationality": "Montenegrin"
    },
    {
      "numeric": 663,
      "id": "MF",
      "cca3": "MAF",
      "title": "Saint-Martin (France)",
      "nationality": "Saint-Martinoise"
    },
    {
      "numeric": 450,
      "id": "MG",
      "cca3": "MDG",
      "title": "Madagascar",
      "nationality": "Malagasy"
    },
    {
      "numeric": 584,
      "id": "MH",
      "cca3": "MHL",
      "title": "Marshall Islands",
      "nationality": "Marshallese"
    },
    {
      "numeric": 807,
      "id": "MK",
      "cca3": "MKD",
      "title": "Macedonia",
      "nationality": "Macedonian"
    },
    {
      "numeric": 466,
      "id": "ML",
      "cca3": "MLI",
      "title": "Mali",
      "nationality": "Malian, Malinese"
    },
    {
      "numeric": 104,
      "id": "MM",
      "cca3": "MMR",
      "title": "Myanmar",
      "nationality": "Burmese"
    },
    {
      "numeric": 496,
      "id": "MN",
      "cca3": "MNG",
      "title": "Mongolia",
      "nationality": "Mongolian"
    },
    {
      "numeric": 446,
      "id": "MO",
      "cca3": "MAC",
      "title": "Macau",
      "nationality": "Macanese, Chinese"
    },
    {
      "numeric": 580,
      "id": "MP",
      "cca3": "MNP",
      "title": "Northern Mariana Islands",
      "nationality": "Northern Marianan"
    },
    {
      "numeric": 474,
      "id": "MQ",
      "cca3": "MTQ",
      "title": "Martinique",
      "nationality": "Martiniquais, Martinican"
    },
    {
      "numeric": 478,
      "id": "MR",
      "cca3": "MRT",
      "title": "Mauritania",
      "nationality": "Mauritanian"
    },
    {
      "numeric": 500,
      "id": "MS",
      "cca3": "MSR",
      "title": "Montserrat",
      "nationality": "Montserratian"
    },
    {
      "numeric": 470,
      "id": "MT",
      "cca3": "MLT",
      "title": "Malta",
      "nationality": "Maltese"
    },
    {
      "numeric": 480,
      "id": "MU",
      "cca3": "MUS",
      "title": "Mauritius",
      "nationality": "Mauritian"
    },
    {
      "numeric": 462,
      "id": "MV",
      "cca3": "MDV",
      "title": "Maldives",
      "nationality": "Maldivian"
    },
    {
      "numeric": 454,
      "id": "MW",
      "cca3": "MWI",
      "title": "Malawi",
      "nationality": "Malawian"
    },
    {
      "numeric": 484,
      "id": "MX",
      "cca3": "MEX",
      "title": "Mexico",
      "nationality": "Mexican"
    },
    {
      "numeric": 458,
      "id": "MY",
      "cca3": "MYS",
      "title": "Malaysia",
      "nationality": "Malaysian"
    },
    {
      "numeric": 508,
      "id": "MZ",
      "cca3": "MOZ",
      "title": "Mozambique",
      "nationality": "Mozambican"
    },
    {
      "numeric": 516,
      "id": "NA",
      "cca3": "NAM",
      "title": "Namibia",
      "nationality": "Namibian"
    },
    {
      "numeric": 540,
      "id": "NC",
      "cca3": "NCL",
      "title": "New Caledonia",
      "nationality": "New Caledonian"
    },
    {
      "numeric": 562,
      "id": "NE",
      "cca3": "NER",
      "title": "Niger",
      "nationality": "Nigerien"
    },
    {
      "numeric": 574,
      "id": "NF",
      "cca3": "NFK",
      "title": "Norfolk Island",
      "nationality": "Norfolk Island"
    },
    {
      "numeric": 566,
      "id": "NG",
      "cca3": "NGA",
      "title": "Nigeria",
      "nationality": "Nigerian"
    },
    {
      "numeric": 558,
      "id": "NI",
      "cca3": "NIC",
      "title": "Nicaragua",
      "nationality": "Nicaraguan"
    },
    {
      "numeric": 528,
      "id": "NL",
      "cca3": "NLD",
      "title": "The Netherlands",
      "nationality": "Dutch, Netherlandic"
    },
    {
      "numeric": 578,
      "id": "NO",
      "cca3": "NOR",
      "title": "Norway",
      "nationality": "Norwegian"
    },
    {
      "numeric": 524,
      "id": "NP",
      "cca3": "NPL",
      "title": "Nepal",
      "nationality": "Nepali, Nepalese"
    },
    {
      "numeric": 520,
      "id": "NR",
      "cca3": "NRU",
      "title": "Nauru",
      "nationality": "Nauruan"
    },
    {
      "numeric": 570,
      "id": "NU",
      "cca3": "NIU",
      "title": "Niue",
      "nationality": "Niuean"
    },
    {
      "numeric": 554,
      "id": "NZ",
      "cca3": "NZL",
      "title": "New Zealand",
      "nationality": "New Zealand, NZ"
    },
    {
      "numeric": 512,
      "id": "OM",
      "cca3": "OMN",
      "title": "Oman",
      "nationality": "Omani"
    },
    {
      "numeric": 591,
      "id": "PA",
      "cca3": "PAN",
      "title": "Panama",
      "nationality": "Panamanian"
    },
    {
      "numeric": 604,
      "id": "PE",
      "cca3": "PER",
      "title": "Peru",
      "nationality": "Peruvian"
    },
    {
      "numeric": 258,
      "id": "PF",
      "cca3": "PYF",
      "title": "French Polynesia",
      "nationality": "French Polynesian"
    },
    {
      "numeric": 598,
      "id": "PG",
      "cca3": "PNG",
      "title": "Papua New Guinea",
      "nationality": "Papua New Guinean, Papuan"
    },
    {
      "numeric": 608,
      "id": "PH",
      "cca3": "PHL",
      "title": "Philippines",
      "nationality": "Philippine, Filipino"
    },
    {
      "numeric": 586,
      "id": "PK",
      "cca3": "PAK",
      "title": "Pakistan",
      "nationality": "Pakistani"
    },
    {
      "numeric": 616,
      "id": "PL",
      "cca3": "POL",
      "title": "Poland",
      "nationality": "Polish"
    },
    {
      "numeric": 666,
      "id": "PM",
      "cca3": "SPM",
      "title": "St. Pierre and Miquelon",
      "nationality": "Saint-Pierrais or Miquelonnais"
    },
    {
      "numeric": 612,
      "id": "PN",
      "cca3": "PCN",
      "title": "Pitcairn",
      "nationality": "Pitcairn Island"
    },
    {
      "numeric": 630,
      "id": "PR",
      "cca3": "PRI",
      "title": "Puerto Rico",
      "nationality": "Puerto Rican"
    },
    {
      "numeric": 275,
      "id": "PS",
      "cca3": "PSE",
      "title": "Palestine, State of",
      "nationality": "Palestinian"
    },
    {
      "numeric": 620,
      "id": "PT",
      "cca3": "PRT",
      "title": "Portugal",
      "nationality": "Portuguese"
    },
    {
      "numeric": 585,
      "id": "PW",
      "cca3": "PLW",
      "title": "Palau",
      "nationality": "Palauan"
    },
    {
      "numeric": 600,
      "id": "PY",
      "cca3": "PRY",
      "title": "Paraguay",
      "nationality": "Paraguayan"
    },
    {
      "numeric": 634,
      "id": "QA",
      "cca3": "QAT",
      "title": "Qatar",
      "nationality": "Qatari"
    },
    {
      "numeric": 638,
      "id": "RE",
      "cca3": "REU",
      "title": "Réunion",
      "nationality": "Réunionese, Réunionnais"
    },
    {
      "numeric": 642,
      "id": "RO",
      "cca3": "ROU",
      "title": "Romania",
      "nationality": "Romanian"
    },
    {
      "numeric": 688,
      "id": "RS",
      "cca3": "SRB",
      "title": "Serbia",
      "nationality": "Serbian"
    },
    {
      "numeric": 643,
      "id": "RU",
      "cca3": "RUS",
      "title": "Russian Federation",
      "nationality": "Russian"
    },
    {
      "numeric": 646,
      "id": "RW",
      "cca3": "RWA",
      "title": "Rwanda",
      "nationality": "Rwandan"
    },
    {
      "numeric": 682,
      "id": "SA",
      "cca3": "SAU",
      "title": "Saudi Arabia",
      "nationality": "Saudi, Saudi Arabian"
    },
    {
      "numeric": 90,
      "id": "SB",
      "cca3": "SLB",
      "title": "Solomon Islands",
      "nationality": "Solomon Island"
    },
    {
      "numeric": 690,
      "id": "SC",
      "cca3": "SYC",
      "title": "Seychelles",
      "nationality": "Seychellois"
    },
    {
      "numeric": 729,
      "id": "SD",
      "cca3": "SDN",
      "title": "Sudan",
      "nationality": "Sudanese"
    },
    {
      "numeric": 752,
      "id": "SE",
      "cca3": "SWE",
      "title": "Sweden",
      "nationality": "Swedish"
    },
    {
      "numeric": 702,
      "id": "SG",
      "cca3": "SGP",
      "title": "Singapore",
      "nationality": "Singaporean"
    },
    {
      "numeric": 654,
      "id": "SH",
      "cca3": "SHN",
      "title": "Saint Helena",
      "nationality": "Saint Helenian"
    },
    {
      "numeric": 705,
      "id": "SI",
      "cca3": "SVN",
      "title": "Slovenia",
      "nationality": "Slovenian, Slovene"
    },
    {
      "numeric": 744,
      "id": "SJ",
      "cca3": "SJM",
      "title": "Svalbard and Jan Mayen Islands",
      "nationality": "Svalbard"
    },
    {
      "numeric": 703,
      "id": "SK",
      "cca3": "SVK",
      "title": "Slovakia",
      "nationality": "Slovak"
    },
    {
      "numeric": 694,
      "id": "SL",
      "cca3": "SLE",
      "title": "Sierra Leone",
      "nationality": "Sierra Leonean"
    },
    {
      "numeric": 674,
      "id": "SM",
      "cca3": "SMR",
      "title": "San Marino",
      "nationality": "Sammarinese"
    },
    {
      "numeric": 686,
      "id": "SN",
      "cca3": "SEN",
      "title": "Senegal",
      "nationality": "Senegalese"
    },
    {
      "numeric": 706,
      "id": "SO",
      "cca3": "SOM",
      "title": "Somalia",
      "nationality": "Somali, Somalian"
    },
    {
      "numeric": 740,
      "id": "SR",
      "cca3": "SUR",
      "title": "Suriname",
      "nationality": "Surinamese"
    },
    {
      "numeric": 728,
      "id": "SS",
      "cca3": "SSD",
      "title": "South Sudan",
      "nationality": "South Sudanese"
    },
    {
      "numeric": 678,
      "id": "ST",
      "cca3": "STP",
      "title": "Sao Tome and Principe",
      "nationality": "São Toméan"
    },
    {
      "numeric": 222,
      "id": "SV",
      "cca3": "SLV",
      "title": "El Salvador",
      "nationality": "Salvadoran"
    },
    {
      "numeric": 534,
      "id": "SX",
      "cca3": "SXM",
      "title": "Sint Maarten (Dutch part)",
      "nationality": "Sint Maarten"
    },
    {
      "numeric": 760,
      "id": "SY",
      "cca3": "SYR",
      "title": "Syria",
      "nationality": "Syrian"
    },
    {
      "numeric": 748,
      "id": "SZ",
      "cca3": "SWZ",
      "title": "Swaziland",
      "nationality": "Swazi"
    },
    {
      "numeric": 796,
      "id": "TC",
      "cca3": "TCA",
      "title": "Turks and Caicos Islands",
      "nationality": "Turks and Caicos Island"
    },
    {
      "numeric": 148,
      "id": "TD",
      "cca3": "TCD",
      "title": "Chad",
      "nationality": "Chadian"
    },
    {
      "numeric": 260,
      "id": "TF",
      "cca3": "ATF",
      "title": "French Southern Territories",
      "nationality": "French Southern Territories"
    },
    {
      "numeric": 768,
      "id": "TG",
      "cca3": "TGO",
      "title": "Togo",
      "nationality": "Togolese"
    },
    {
      "numeric": 764,
      "id": "TH",
      "cca3": "THA",
      "title": "Thailand",
      "nationality": "Thai"
    },
    {
      "numeric": 762,
      "id": "TJ",
      "cca3": "TJK",
      "title": "Tajikistan",
      "nationality": "Tajikistani"
    },
    {
      "numeric": 772,
      "id": "TK",
      "cca3": "TKL",
      "title": "Tokelau",
      "nationality": "Tokelauan"
    },
    {
      "numeric": 626,
      "id": "TL",
      "cca3": "TLS",
      "title": "Timor-Leste",
      "nationality": "Timorese"
    },
    {
      "numeric": 795,
      "id": "TM",
      "cca3": "TKM",
      "title": "Turkmenistan",
      "nationality": "Turkmen"
    },
    {
      "numeric": 788,
      "id": "TN",
      "cca3": "TUN",
      "title": "Tunisia",
      "nationality": "Tunisian"
    },
    {
      "numeric": 776,
      "id": "TO",
      "cca3": "TON",
      "title": "Tonga",
      "nationality": "Tongan"
    },
    {
      "numeric": 792,
      "id": "TR",
      "cca3": "TUR",
      "title": "Turkey",
      "nationality": "Turkish"
    },
    {
      "numeric": 780,
      "id": "TT",
      "cca3": "TTO",
      "title": "Trinidad and Tobago",
      "nationality": "Trinidadian or Tobagonian"
    },
    {
      "numeric": 798,
      "id": "TV",
      "cca3": "TUV",
      "title": "Tuvalu",
      "nationality": "Tuvaluan"
    },
    {
      "numeric": 158,
      "id": "TW",
      "cca3": "TWN",
      "title": "Taiwan",
      "nationality": "Chinese, Taiwanese"
    },
    {
      "numeric": 834,
      "id": "TZ",
      "cca3": "TZA",
      "title": "Tanzania",
      "nationality": "Tanzanian"
    },
    {
      "numeric": 804,
      "id": "UA",
      "cca3": "UKR",
      "title": "Ukraine",
      "nationality": "Ukrainian"
    },
    {
      "numeric": 800,
      "id": "UG",
      "cca3": "UGA",
      "title": "Uganda",
      "nationality": "Ugandan"
    },
    {
      "numeric": 581,
      "id": "UM",
      "cca3": "UMI",
      "title": "United States Minor Outlying Islands",
      "nationality": "American"
    },
    {
      "numeric": 840,
      "id": "US",
      "cca3": "USA",
      "title": "United States",
      "nationality": "American"
    },
    {
      "numeric": 858,
      "id": "UY",
      "cca3": "URY",
      "title": "Uruguay",
      "nationality": "Uruguayan"
    },
    {
      "numeric": 860,
      "id": "UZ",
      "cca3": "UZB",
      "title": "Uzbekistan",
      "nationality": "Uzbekistani, Uzbek"
    },
    {
      "numeric": 336,
      "id": "VA",
      "cca3": "VAT",
      "title": "Vatican",
      "nationality": "Vatican"
    },
    {
      "numeric": 670,
      "id": "VC",
      "cca3": "VCT",
      "title": "Saint Vincent and the Grenadines",
      "nationality": "Saint Vincentian, Vincentian"
    },
    {
      "numeric": 862,
      "id": "VE",
      "cca3": "VEN",
      "title": "Venezuela",
      "nationality": "Venezuelan"
    },
    {
      "numeric": 92,
      "id": "VG",
      "cca3": "VGB",
      "title": "Virgin Islands (British)",
      "nationality": "British Virgin Island"
    },
    {
      "numeric": 850,
      "id": "VI",
      "cca3": "VIR",
      "title": "Virgin Islands (U.S.)",
      "nationality": "U.S. Virgin Island"
    },
    {
      "numeric": 704,
      "id": "VN",
      "cca3": "VNM",
      "title": "Vietnam",
      "nationality": "Vietnamese"
    },
    {
      "numeric": 548,
      "id": "VU",
      "cca3": "VUT",
      "title": "Vanuatu",
      "nationality": "Ni-Vanuatu, Vanuatuan"
    },
    {
      "numeric": 876,
      "id": "WF",
      "cca3": "WLF",
      "title": "Wallis and Futuna Islands",
      "nationality": "Wallis and Futuna, Wallisian or Futunan"
    },
    {
      "numeric": 882,
      "id": "WS",
      "cca3": "WSM",
      "title": "Samoa",
      "nationality": "Samoan"
    },
    {
      "numeric": 887,
      "id": "YE",
      "cca3": "YEM",
      "title": "Yemen",
      "nationality": "Yemeni"
    },
    {
      "numeric": 175,
      "id": "YT",
      "cca3": "MYT",
      "title": "Mayotte",
      "nationality": "Mahoran"
    },
    {
      "numeric": 710,
      "id": "ZA",
      "cca3": "ZAF",
      "title": "South Africa",
      "nationality": "South African"
    },
    {
      "numeric": 894,
      "id": "ZM",
      "cca3": "ZMB",
      "title": "Zambia",
      "nationality": "Zambian"
    },
    {
      "numeric": 716,
      "id": "ZW",
      "cca3": "ZWE",
      "title": "Zimbabwe",
      "nationality": "Zimbabwean"
    },
    {
      "numeric": 383,
      "id": "XK",
      "cca3": "RKS",
      "title": "Kosovo",
      "nationality": "Kosovar"
    }
  ]
}