{
  "id": "tradle.StylesPack",
  "title": "Styles Pack",
  "interfaces": [
    "tradle.Message"
  ],
  "type": "tradle.Model",
  "properties": {
    "linkColor": {
      "type": "string"
    },
    "productRowBgColor": {
      "type": "string"
    },
    "productRowTextColor": {
      "type": "string"
    },
    "sharedWithBg": {
      "type": "string"
    },
    "sharedWithVerificationBg": {
      "type": "string"
    },
    "verifiedHeaderColor": {
      "type": "string"
    },
    "verifiedLinkColor": {
      "type": "string"
    },
    "verificationBg": {
      "type": "string"
    },
    "verifiedSourcesColor": {
      "type": "string"
    },
    "confirmationColor": {
      "type": "string"
    },
    "confirmationBg": {
      "type": "string"
    },
    "requestFulfilled": {
      "type": "string"
    },
    "backgroundColor": {
      "type": "string"
    },
    "productBgColor": {
      "type": "string"
    },
    "myMessageLinkColor": {
      "type": "string"
    },
    "myMessageBackgroundColor": {
      "type": "string"
    },
    "formErrorBorder": {
      "type": "string"
    },
    "formErrorColor": {
      "type": "string"
    },
    "formErrorBg": {
      "type": "string"
    },
    "structuredMessageBackgroundColor": {
      "type": "string"
    },
    "structuredMessageColor": {
      "type": "string"
    },
    "structuredMessageBorder": {
      "type": "string"
    },
    "shareContextTextColor": {
      "type": "string"
    },
    "shareContextBackgroundColor": {
      "type": "string"
    },
    "currentContextTextColor": {
      "type": "string"
    },
    "currentContextBackgroundColor": {
      "type": "string"
    },
    "contextBackgroundColor": {
      "type": "string"
    },
    "contextTextColor": {
      "type": "string"
    },
    "shareButtonBackgroundColor": {
      "type": "string"
    },
    "backlinkRowBgColor": {
      "type": "string"
    },
    "backlinkRowTextColor": {
      "type": "string"
    },
    "listBg": {
      "type": "string"
    },
    "listColor": {
      "type": "string"
    },
    "sourcedVerificationBgColor": {
      "type": "string"
    },
    "sourcedVerificationTextColor": {
      "type": "string"
    },
    "navBarBackgroundColor": {
      "type": "string"
    },
    "navBarBorderColor": {
      "type": "string"
    },
    "navBarBorderWidth": {
      "type": "number"
    }
  }
}
